{
  "months": [
    {
      "id": 1,
      "month": "12월"
    },
    {
      "id": 2,
      "month": "1월"
    },
    {
      "id": 3,
      "month": "2월"
    }
  ],
  "courses": [
    {
      "id": 1,
      "deadline": true,
      "month": "12월",
      "title": "[BIM]건축 설계",
      "day": "2021년 12월 28일"
    },
    {
      "id": 2,
      "deadline": false,
      "month": "12월",
      "title": "[BIM]건축 설계",
      "day": "2021년 12월 28일"
    },
    {
      "id": 3,
      "deadline": true,
      "month": "1월",
      "title": "[BIM]건축 설계",
      "day": "2021년 1월 28일"
    },
    {
      "id": 4,
      "month": "1월",
      "title": "[BIM]건축 설계",
      "deadline": true,
      "day": "2022년 1월 12일"
    },
    {
      "id": 5,
      "deadline": false,
      "month": "2월",
      "title": "새로운과정입니다.",
      "day": "2022년 2월 15일"
    },
    {
      "id": 10,
      "deadline": false,
      "month": "2월",
      "title": "새과정",
      "day": "2022년 2월 19일"
    },
    {
      "id": 11,
      "deadline": false,
      "month": "2월",
      "title": "새새과정",
      "day": "2022년 2월 20일"
    },
    {
      "id": 12,
      "deadline": false,
      "month": "12월",
      "title": "dd",
      "day": "dddddd"
    },
    {
      "id": 13,
      "deadline": false,
      "month": "12월",
      "title": "dd",
      "day": "dddddd"
    }
  ]
}